flask_async_mail/__init__.py
flask_async_mail/celery_ext.py
flask_async_mail/demo.py
flask_async_mail/email_service.py
flask_async_mail/version.py
flask_async_mail-0.1.0.dist-info/LICENSE
flask_async_mail-0.1.0.dist-info/METADATA
flask_async_mail-0.1.0.dist-info/WHEEL
flask_async_mail-0.1.0.dist-info/RECORD
