Metadata-Version: 2.3
Name: flask-async-mail
Version: 0.1.0
Summary: A Flask extension for sending emails asynchronously with Celery
Author: manitreasure1
Author-email: manitreasure1@gmail.com
Requires-Python: >=3.13
Classifier: Programming Language :: Python :: 3
Classifier: Programming Language :: Python :: 3.13
Requires-Dist: aiosmtpd (>=1.4.6,<2.0.0)
Requires-Dist: aiosmtplib (>=4.0.0,<5.0.0)
Requires-Dist: celery (>=5.4.0,<6.0.0)
Requires-Dist: email-validator (>=2.2.0,<3.0.0)
Requires-Dist: flask[async] (>=3.1.0,<4.0.0)
Requires-Dist: python-dotenv (>=1.0.1,<2.0.0)
Requires-Dist: redis (>=5.2.1,<6.0.0)
